{
    "IdentityFeatureTransferAdvanced": {
        "title": "FLUX.2 Klein身份特征迁移高级",
        "inputs": {
            "model": "模型",
            "subject_mask": "主体遮罩"
        },
        "widgets": {
            "reference_index": "参考索引",
            "mode": "模式",
            "top_k_percent": "前K百分比",
            "double_enable": "双模式启用",
            "double_strength": "双模式强度",
            "double_start": "双模式开始",
            "double_end": "双模式结束",
            "single_enable": "单模式启用",
            "single_strength": "单模式强度",
            "single_start": "单模式开始",
            "single_end": "单模式结束",
            "block_schedule": "块调度",
            "sim_floor": "相似度下限",
            "mask_threshold": "遮罩阈值"
        },
        "outputs": {},
        "description": "FLUX.2 Klein身份特征迁移高级节点"
    },
    "Flux2KleinKSampler": {
        "title": "FLUX.2 Klein K采样器",
        "inputs": {
            "model": "模型",
            "positive": "正面提示词",
            "negative": "负面提示词",
            "latent_image": "图像Latent"
        },
        "widgets": {
            "steps": "步数",
            "guidance_scale": "引导比例",
            "seed": "种子",
            "denoise": "去噪",
            "base_shift": "基础偏移",
            "max_shift": "最大偏移"
        },
        "outputs": {},
        "description": "FLUX.2 Klein KSampler 节点用于在Latent空间中进行图像生成。"
    },
    "IdentityFeatureTransfer": {
        "title": "FLUX.2 Klein身份特征迁移",
        "inputs": {
            "model": "模型"
        },
        "widgets": {
            "strength": "强度",
            "start_block": "起始块",
            "end_block": "结束块",
            "mode": "模式",
            "top_k_percent": "top_k 百分比"
        },
        "outputs": {},
        "description": "FLUX.2 Klein身份特征迁移节点"
    },
    "IdentityGuidance": {
        "title": "FLUX.2 Klein身份引导",
        "inputs": {
            "model": "模型",
            "identity_latent": "身份Latent"
        },
        "widgets": {
            "strength": "强度",
            "start_percent": "开始百分比",
            "end_percent": "结束百分比",
            "mode": "模式"
        },
        "outputs": {},
        "description": "用于在FLUX.2模型中应用Klein身份引导的节点"
    },
    "Flux2KleinColorAnchor": {
        "title": "Flux2 Klein色彩锚点",
        "inputs": {
            "model": "模型",
            "conditioning": "条件"
        },
        "widgets": {
            "strength": "强度",
            "ramp_curve": "斜坡曲线",
            "ref_index": "参考索引",
            "channel_weights": "通道权重",
            "debug": "调试"
        },
        "outputs": {
            "MODEL": "模型"
        },
        "description": "",
        "api_version": "V1"
    },
    "FluxxKleinEnhancer": {
        "title": "Flux2 Klein增强器",
        "inputs": {
            "conditioning": "条件"
        },
        "widgets": {
            "magnitude": "幅度",
            "contrast": "对比度",
            "normalize_strength": "标准化强度",
            "preserve_original": "保留原始",
            "preserve_mode": "保留模式",
            "edit_text_weight": "编辑文本权重",
            "active_end_override": "激活结束覆盖",
            "low_vram": "低显存",
            "device": "设备",
            "debug": "调试"
        },
        "outputs": {
            "CONDITIONING": "条件"
        },
        "description": "FLUX. .Klein 条件增强器。\n\n操作包括：\n- 幅度：直接缩放活动区域嵌入\n- 对比度：放大标记之间的差异\n- 标准化：等量标记大小\n- 保留原始：以多种模式混合回原始嵌入\n\n所有操作只修改活动文本区域（填充部分未受影响）。",
        "api_version": "V1"
    },
    "FluxxKleinDetailController": {
        "title": "Flux2 Klein细节控制器",
        "inputs": {
            "conditioning": "条件"
        },
        "widgets": {
            "front_mult": "前部倍数",
            "mid_mult": "中部倍数",
            "end_mult": "结尾倍数",
            "emphasis_start": "强调开始",
            "emphasis_end": "强调结束",
            "emphasis_mult": "强调倍数",
            "preserve_original": "保留原始",
            "preserve_mode": "保留模式",
            "low_vram": "低显存",
            "device": "设备",
            "debug": "调试"
        },
        "outputs": {
            "CONDITIONING": "条件"
        },
        "description": "FLUX. .Klein 条件的区域控制。\n\n将活动标记分为区域：\n- 前部：主题/主要概念\n- 中部：详细信息/修饰符\n- 结尾：风格/质量术语",
        "api_version": "V1"
    },
    "Flux2KleinMaskRefController": {
        "title": "Flux2 Klein遮罩引用控制器",
        "inputs": {
            "conditioning": "条件",
            "mask": "遮罩"
        },
        "widgets": {
            "strength": "强度",
            "invert_mask": "反转遮罩",
            "feather": "羽化",
            "channel_mode": "通道模式",
            "debug": "调试"
        },
        "outputs": {
            "CONDITIONING": "条件"
        },
        "description": "使用绘制的遮罩空间地控制参考Latent。\n\n插入任何遮罩（来自 MaskEditor、分割、SAM 等），然后将其连接到\n遮罩输入。节点会调整其尺寸以匹配参考Latent的空间维度，并按通道相乘。\n\n典型用法：\n  - 在您希望保持不变的主题上绘制白色\n  - 在文本提示应接管的区域上留黑色\n  - 将此节点连接在您的 FLUX. .Klein 编码和 KSampler 之间",
        "api_version": "V1"
    },
    "FluxxKleinRefLatentController": {
        "title": "Flux2 Klein参考Latent控制器",
        "inputs": {
            "model": "模型",
            "conditioning": "条件"
        },
        "widgets": {
            "strength": "强度",
            "reference_index": "参考索引",
            "spatial_fade": "空间淡化",
            "spatial_fade_strength": "空间淡化强度",
            "debug": "调试"
        },
        "outputs": {
            "MODEL": "模型",
            "CONDITIONING": "条件"
        },
        "description": "",
        "api_version": "V1"
    },
    "FluxxKleinTextRefBalance": {
        "title": "Flux2 Klein文本与参考平衡",
        "inputs": {
            "model": "模型",
            "conditioning": "条件"
        },
        "widgets": {
            "balance": "平衡",
            "debug": "调试"
        },
        "outputs": {
            "MODEL": "模型",
            "CONDITIONING": "条件"
        },
        "description": "",
        "api_version": "V1"
    },
    "Flux2KleinRefLatentWeight": {
        "title": "Flux2 Klein参考Latent权重",
        "inputs": {
            "model": "模型"
        },
        "widgets": {
            "reference_index": "参考索引",
            "weight": "权重"
        },
        "outputs": {
            "MODEL": "模型"
        },
        "description": "",
        "api_version": "V1"
    },
    "FluxxKleinTextEnhancer": {
        "title": "Flux2 Klein文本增强器",
        "inputs": {
            "conditioning": "条件"
        },
        "widgets": {
            "magnitude": "幅度",
            "contrast": "对比度",
            "normalize_strength": "标准化强度",
            "skip_bos": "跳过起始符号",
            "debug": "调试"
        },
        "outputs": {
            "CONDITIONING": "条件"
        },
        "description": "修改文本条件标记。\n\n操作顺序：\n1. 标准化：等量标记大小\n2. 对比度：放大/减少标记间的差异\n3. 幅度：全局缩放",
        "api_version": "V1"
    },
    "Flux2KleinSectionedEncoder": {
        "title": "Flux2 Klein分段编码器",
        "inputs": {
            "clip": "剪辑"
        },
        "widgets": {
            "front_text": "前端文本",
            "mid_text": "中间文本",
            "end_text": "末端文本",
            "combined_prompt": "组合提示",
            "show_preview": "显示预览",
            "debug": "调试",
            "mode": "模式",
            "separator": "分隔符"
        },
        "outputs": {
            "conditioning": "条件",
            "front_section": "前端部分",
            "mid_section": "中间部分",
            "end_section": "末端部分",
            "full_prompt": "完整提示"
        },
        "description": "结构化文本输入节点。\n 将提示词分为前、中、后三段进行输入与组合，便于搭配细节控制器（Detail Controller）精确控制画面不同元素的生成优先级和权重。"
    },
    "Flux2KleinEnhancer": {
        "title": "Flux2 Klein增强器",
        "inputs": {
            "conditioning": "条件"
        },
        "widgets": {
            "magnitude": "幅度",
            "contrast": "对比度",
            "normalize_strength": "标准化强度",
            "preserve_original": "保留原始",
            "edit_text_weight": "文本编辑权重",
            "active_end_override": "激活结束重置",
            "low_vram": "低显存",
            "debug": "调试",
            "preserve_mode": "保留模式",
            "device": "设备"
        },
        "outputs": {
            "CONDITIONING": "条件"
        },
        "description": "核心多合一增强节点。\n 用于综合控制 Flux2Klein 模型的提示词遵循度、对比度以及文本与图像的编辑权重，是介入并修改底层特征流的主要入口。"
    },
    "Flux2KleinDetailController": {
        "title": "Flux2 Klein细节控制器",
        "inputs": {
            "conditioning": "条件"
        },
        "widgets": {
            "front_mult": "前端多",
            "mid_mult": "中端多",
            "end_mult": "末端多",
            "emphasis_start": "强调开始",
            "emphasis_end": "强调结束",
            "emphasis_mult": "强调多",
            "preserve_original": "保留原始",
            "low_vram": "低显存",
            "debug": "调试",
            "preserve_mode": "保留模式",
            "device": "设备"
        },
        "outputs": {
            "CONDITIONING": "条件"
        },
        "description": "精细化文本权重控制节点。\n 允许分别对提示词的前端、中端、末端部分进行独立的强度调整（乘数缩放），并在指定的步数范围内针对性地强调特定细节。"
    },
    "Flux2KleinRefLatentController": {
        "title": "Flux2 Klein参考Latent控制器",
        "inputs": {
            "conditioning": "条件"
        },
        "widgets": {
            "strength": "强度",
            "blend_with_noise": "与噪声混合",
            "channel_mask_start": "通道遮罩开始",
            "channel_mask_end": "通道遮罩结束",
            "spatial_fade": "空间淡入",
            "spatial_fade_strength": "空间淡入强度",
            "debug": "调试"
        },
        "outputs": {
            "CONDITIONING": "条件"
        },
        "description": "针对图像流（img_stream）的高级结构控制节点。\n 支持调整参考图与噪声的混合比例、应用特定的通道遮罩，以及通过空间渐变（如中心、边缘、上下）来控制参考图对生成画面的空间影响。"
    },
    "Flux2KleinTextRefBalance": {
        "title": "Flux2 Klein文本参考平衡器",
        "inputs": {
            "conditioning": "条件"
        },
        "widgets": {
            "balance": "平衡",
            "debug": "调试"
        },
        "outputs": {
            "CONDITIONING": "条件"
        },
        "description": "动态平衡控制节点。\n 用于一键调节文本特征（txt_stream）与图像参考特征（img_stream）之间的权重比例，决定生成画面是更贴近文本描述还是更忠于参考图像。"
    },
    "Flux2KleinTextEnhancer": {
        "title": "Flux2 Klein文本增强器",
        "inputs": {
            "conditioning": "条件"
        },
        "widgets": {
            "magnitude": "幅度",
            "contrast": "对比度",
            "normalize_strength": "标准化强度",
            "skip_bos": "跳过BOS",
            "debug": "调试"
        },
        "outputs": {
            "CONDITIONING": "条件"
        },
        "description": "专注文本流（txt_stream）的增强节点。\n 通过放大特征幅度和调整对比度来显著强化文本提示词的影响力，支持跳过序列起始符（BOS）以获得更纯粹的文本引导。"
    }
}