{
  "使用预设": "Use Preset",
  "手动输入": "Manual Input",
  "写实风格": "Realistic Style",
  "像素风格": "Pixel Style",
  "油画风格": "Oil Painting Style",
  "版画风格": "Printmaking Style",
  "壁画风格": "Fresco Style",
  "素描风格": "Sketch Style",
  "黑白电影风格": "Black and White Film Style",
  "科幻风格": "Sci-Fi Style",
  "抽象风格": "Abstract Style",
  "迷幻风格": "Psychedelic Style",
  "文艺复兴": "Renaissance",
  "水彩风格": "Watercolor Style",
  "赛博朋克风格": "Cyberpunk Style",
  "动漫风格": "Anime Style",
  "中国水墨风格": "Chinese Ink Wash Style",
  "中式传统风格": "Traditional Chinese Style",
  "黑白动画风格": "Black and White Animation Style",
  "浮世绘风格": "Ukiyo-e Style",
  "点彩派风格": "Pointillism Style",
  "蒸汽朋克风格": "Steampunk Style",
  "皮克斯风格": "Pixar Style",
  "吉卜力风格": "Ghibli Style",
  "迪士尼风格": "Disney Style",
  "美漫风格": "American Comic Style",
  "故障艺术风格": "Glitch Art Style",
  "全息投影效果": "Holographic Effect",
  "数据可视化风格": "Data Visualization Style",
  "UI界面风格": "UI Interface Style",
  "毛毡风格": "Felt Style",
  "3D卡通风格": "3D Cartoon Style",
  "木偶动画风格": "Puppet Animation Style",
  "3D游戏风格": "3D Game Style",
  "黏土风格": "Claymation Style",
  "二次元风格": "2D Style",
  "低多边形风格": "Low Poly Style",
  "印度风格": "Indian Style",
  "阿拉伯风格": "Arabian Style",
  "印第安风格": "Indigenous American Style",
  "非洲部落风格": "African Tribal Style",
  "东南亚风格": "Southeast Asian Style",
  "大远景": "Extreme Long Shot",
  "远景": "Long Shot",
  "全景": "Full Shot",
  "中景": "Medium Shot",
  "中近景": "Medium Close-Up",
  "半身景": "Bust Shot",
  "近景": "Close-Up",
  "特写": "Extreme Close-Up",
  "大特写": "Macro Close-Up",
  "黄金分割构图": "Golden Ratio Composition",
  "对称构图": "Symmetrical Composition",
  "三分法构图": "Rule of Thirds Composition",
  "对角线构图": "Diagonal Composition",
  "三角形构图": "Triangular Composition",
  "S形构图": "S-Curve Composition",
  "框式构图": "Frame within a Frame",
  "放射式构图": "Radial Composition",
  "紧凑式构图": "Tight Composition",
  "留白构图": "Negative Space Composition",
  "X形构图": "X-Shape Composition",
  "L形构图": "L-Shape Composition",
  "隧道构图": "Tunnel Composition",
  "中心构图": "Center Composition",
  "平衡构图": "Balanced Composition",
  "右侧重构图": "Right-Weighted Composition",
  "左侧重构图": "Left-Weighted Composition",
  "短边构图": "Short Edge Composition",
  "随机": "Random",
  "微笑": "Smile",
  "大笑": "Laugh",
  "中性": "Neutral",
  "无随机": "No Random",
  "无": "None",
  "奶油樱花": "Creamy Sakura",
  "香芋奶茶": "Taro Milk Tea",
  "莫兰迪粉灰": "Morandi Pink Gray",
  "粉金大理石": "Pink Gold Marble",
  "午夜芭蕾": "Midnight Ballet",
  "金属工业粉": "Metallic Industrial Pink",
  "赛博甜心": "Cyber Sweetheart",
  "热带果汁": "Tropical Juice",
  "像素游戏": "Pixel Game",
  "老电影滤镜": "Old Film Filter",
  "70年代迪斯科": "70s Disco",
  "维多利亚宫廷": "Victorian Court",
  "春日花园": "Spring Garden",
  "沙漠黄昏": "Desert Dusk",
  "海盐冰淇淋": "Sea Salt Ice Cream",
  "霓虹故障": "Neon Glitch",
  "液态金属": "Liquid Metal",
  "AI虚拟空间": "AI Virtual Space",
  "经典粉黑": "Classic Pink Black",
  "粉灰进阶": "Advanced Pink Gray",
  "正视图": "Front View",
  "顶视图": "Top View",
  "后视图": "Back View",
  "左视图": "Left View",
  "右视图": "Right View",
  "侧视图": "Side View",
  "黑色": "Black",
  "白色": "White",
  "浅灰色": "Light Gray",
  "深灰色": "Dark Gray",
  "浅蓝色": "Light Blue",
  "深蓝色": "Dark Blue",
  "亮绿色": "Bright Green",
  "深绿色": "Dark Green",
  "紫水晶": "Amethyst",
  "翡翠": "Emerald",
  "霓虹蓝": "Neon Blue",
  "霓虹绿": "Neon Green",
  "霓虹橙": "Neon Orange",
  "霓虹粉": "Neon Pink",
  "霓虹黄": "Neon Yellow",
  "铂金": "Platinum",
  "玫瑰金": "Rose Gold",
  "红宝石": "Ruby",
  "蓝宝石": "Sapphire",
  "黄玉/托帕石": "Topaz",
  "黄色": "Yellow",
  "青色": "Cyan",
  "灰色": "Gray",
  "浅红色": "Light Red",
  "浅绿色": "Light Green",
  "浅黄色": "Light Yellow",
  "浅紫色": "Light Purple",
  "浅青色": "Light Cyan",
  "浅白色": "Off White",
  "爱丽丝蓝": "Alice Blue",
  "古董白": "Antique White",
  "碧绿色": "Aquamarine",
  "天蓝色": "Azure",
  "米色": "Beige",
  "陶坯色": "Bisque",
  "杏仁白": "Blanched Almond",
  "蓝紫罗兰": "Blue Violet",
  "硬木色": "Burly Wood",
  "军校蓝": "Cadet Blue",
  "查特酒绿": "Chartreuse",
  "巧克力色": "Chocolate",
  "矢车菊蓝": "Cornflower Blue",
  "玉米丝色": "Cornsilk",
  "绯红色": "Crimson",
  "深青色": "Dark Cyan",
  "深金菊黄": "Dark Goldenrod",
  "深卡其色": "Dark Khaki",
  "深洋红色": "Dark Magenta",
  "深橄榄绿": "Dark Olive Green",
  "深橙色": "Dark Orange",
  "深兰花紫": "Dark Orchid",
  "深红色": "Dark Red",
  "深鲑鱼红": "Dark Salmon",
  "深海绿色": "Dark Sea Green",
  "深石板蓝": "Dark Slate Blue",
  "深石板灰": "Dark Slate Gray",
  "深绿松石": "Dark Turquoise",
  "深紫罗兰": "Dark Violet",
  "深粉红色": "Deep Pink",
  "深天蓝色": "Deep Sky Blue",
  "暗淡灰": "Dim Gray",
  "道奇蓝": "Dodger Blue",
  "耐火砖红": "Firebrick",
  "花卉白": "Floral White",
  "森林绿": "Forest Green",
  "庚斯博罗灰": "Gainsboro",
  "幽灵白": "Ghost White",
  "金菊黄": "Goldenrod",
  "黄绿色": "Green Yellow",
  "蜜瓜色": "Honeydew",
  "艳粉色": "Hot Pink",
  "印度红": "Indian Red",
  "象牙色": "Ivory",
  "卡其色": "Khaki",
  "薰衣草红": "Lavender Blush",
  "草坪绿": "Lawn Green",
  "柠檬绸": "Lemon Chiffon",
  "浅珊瑚色": "Light Coral",
  "浅粉红色": "Light Pink",
  "浅鲑鱼红": "Light Salmon",
  "浅海绿色": "Light Sea Green",
  "浅天蓝色": "Light Sky Blue",
  "浅石板灰": "Light Slate Gray",
  "浅钢蓝": "Light Steel Blue",
  "酸橙绿": "Lime Green",
  "亚麻色": "Linen",
  "中碧绿色": "Medium Aquamarine",
  "中蓝色": "Medium Blue",
  "中兰花紫": "Medium Orchid",
  "中紫色": "Medium Purple",
  "中海绿色": "Medium Sea Green",
  "中石板蓝": "Medium Slate Blue",
  "中春绿色": "Medium Spring Green",
  "中绿松石": "Medium Turquoise",
  "中紫红": "Medium Violet Red",
  "午夜蓝": "Midnight Blue",
  "薄荷奶油": "Mint Cream",
  "雾玫瑰": "Misty Rose",
  "鹿皮鞋色": "Moccasin",
  "纳瓦白": "Navajo White",
  "海军蓝": "Navy",
  "旧蕾丝": "Old Lace",
  "橄榄褐": "Olive Drab",
  "橙红色": "Orange Red",
  "兰花紫": "Orchid",
  "苍白金菊黄": "Pale Goldenrod",
  "苍白绿": "Pale Green",
  "苍白绿松石": "Pale Turquoise",
  "苍白紫红": "Pale Violet Red",
  "木瓜鞭色": "Papaya Whip",
  "桃粉色": "Peach Puff",
  "秘鲁色": "Peru",
  "李紫色": "Plum",
  "粉末蓝": "Powder Blue",
  "丽贝卡紫": "Rebecca Purple",
  "玫瑰褐": "Rosy Brown",
  "皇家蓝": "Royal Blue",
  "鞍褐色": "Saddle Brown",
  "鲑鱼红": "Salmon",
  "沙褐色": "Sandy Brown",
  "海绿色": "Sea Green",
  "贝壳色": "Seashell",
  "赭色": "Sienna",
  "石板灰": "Slate Gray",
  "zhudefeixingmeng": "猪的飞行梦汉化20260409   18:21更新"
}